nr/__init__.py
nr/functional/__init__.py
nr/functional/py.typed
nr.functional-0.2.0.dist-info/LICENSE.txt
nr.functional-0.2.0.dist-info/METADATA
nr.functional-0.2.0.dist-info/WHEEL
nr.functional-0.2.0.dist-info/top_level.txt
nr.functional-0.2.0.dist-info/RECORD
