Metadata-Version: 2.1
Name: nr.functional
Version: 0.2.0
Summary: Tools for functional programming in Python.
Home-page: https://github.com/NiklasRosenstein/nr-python
Author: Niklas Rosenstein
Author-email: nrosenstein@palantir.com
License: MIT
Platform: UNKNOWN
Requires-Python: >=3.6.0,<4.0.0
